AUTHORS
LICENSE
MANIFEST.in
NEWS
README.rst
setup.cfg
setup.py
doc/Makefile
doc/authors.rst
doc/basic_usage.rst
doc/common.txt
doc/conf.py
doc/design_patterns.rst
doc/environment.rst
doc/examples.rst
doc/history.rst
doc/hubs.rst
doc/index.rst
doc/modules.rst
doc/patching.rst
doc/ssl.rst
doc/testing.rst
doc/threading.rst
doc/zeromq.rst
doc/images/threading_illustration.png
doc/modules/backdoor.rst
doc/modules/corolocal.rst
doc/modules/dagpool.rst
doc/modules/db_pool.rst
doc/modules/debug.rst
doc/modules/event.rst
doc/modules/greenpool.rst
doc/modules/greenthread.rst
doc/modules/pools.rst
doc/modules/queue.rst
doc/modules/semaphore.rst
doc/modules/timeout.rst
doc/modules/websocket.rst
doc/modules/wsgi.rst
doc/modules/zmq.rst
eventlet/__init__.py
eventlet/backdoor.py
eventlet/convenience.py
eventlet/corolocal.py
eventlet/coros.py
eventlet/dagpool.py
eventlet/db_pool.py
eventlet/debug.py
eventlet/event.py
eventlet/greenpool.py
eventlet/greenthread.py
eventlet/patcher.py
eventlet/pools.py
eventlet/queue.py
eventlet/semaphore.py
eventlet/timeout.py
eventlet/tpool.py
eventlet/websocket.py
eventlet/wsgi.py
eventlet/green/BaseHTTPServer.py
eventlet/green/CGIHTTPServer.py
eventlet/green/MySQLdb.py
eventlet/green/Queue.py
eventlet/green/SimpleHTTPServer.py
eventlet/green/SocketServer.py
eventlet/green/__init__.py
eventlet/green/_socket_nodns.py
eventlet/green/asynchat.py
eventlet/green/asyncore.py
eventlet/green/builtin.py
eventlet/green/ftplib.py
eventlet/green/httplib.py
eventlet/green/os.py
eventlet/green/profile.py
eventlet/green/select.py
eventlet/green/selectors.py
eventlet/green/socket.py
eventlet/green/ssl.py
eventlet/green/subprocess.py
eventlet/green/thread.py
eventlet/green/threading.py
eventlet/green/time.py
eventlet/green/urllib2.py
eventlet/green/zmq.py
eventlet/green/OpenSSL/SSL.py
eventlet/green/OpenSSL/__init__.py
eventlet/green/OpenSSL/crypto.py
eventlet/green/OpenSSL/tsafe.py
eventlet/green/OpenSSL/version.py
eventlet/green/http/__init__.py
eventlet_patched.egg-info/PKG-INFO
eventlet_patched.egg-info/SOURCES.txt
eventlet_patched.egg-info/dependency_links.txt
eventlet_patched.egg-info/not-zip-safe
eventlet_patched.egg-info/requires.txt
eventlet_patched.egg-info/top_level.txt
